bullet/__init__.py
bullet/charDef.py
bullet/client.py
bullet/colors.py
bullet/cursor.py
bullet/emojis.py
bullet/keyhandler.py
bullet/styles.py
bullet/utils.py
bullet-2.2.0.dist-info/LICENSE
bullet-2.2.0.dist-info/METADATA
bullet-2.2.0.dist-info/WHEEL
bullet-2.2.0.dist-info/top_level.txt
bullet-2.2.0.dist-info/RECORD
